neurocache/__init__.py
neurocache/auto.py
neurocache/config.py
neurocache/modeling.py
neurocache/neurocache.py
neurocache/cache/__init__.py
neurocache/cache/cache_utils.py
neurocache/cache/config.py
neurocache/cache/ondevice.py
neurocache/utils/__init__.py
neurocache/utils/save_and_load.py
neurocache/utils/types.py
neurocache/utils/utils.py
neurocache-0.0.1.dist-info/LICENSE
neurocache-0.0.1.dist-info/METADATA
neurocache-0.0.1.dist-info/WHEEL
neurocache-0.0.1.dist-info/top_level.txt
neurocache-0.0.1.dist-info/RECORD
