Metadata-Version: 2.1
Name: neurocache
Version: 0.0.1
Summary: Neurocache: A library for augmenting language models with external memory.
Home-page: https://github.com/alisafaya/neurocache
Author: Ali Safaya
Author-email: alisafaya@gmail.com
License: Apache
Keywords: deep learning
Classifier: Intended Audience :: Developers
Classifier: Intended Audience :: Education
Classifier: Intended Audience :: Science/Research
Classifier: License :: OSI Approved :: Apache Software License
Classifier: Operating System :: OS Independent
Classifier: Programming Language :: Python :: 3
Classifier: Programming Language :: Python :: 3.8
Classifier: Topic :: Scientific/Engineering :: Artificial Intelligence
Requires-Python: >=3.8.0
License-File: LICENSE
Requires-Dist: peft (>=0.5.0)
Requires-Dist: numpy (>=1.17)
Requires-Dist: packaging (>=20.0)
Requires-Dist: psutil
Requires-Dist: pyyaml
Requires-Dist: torch (>=1.13.0)
Requires-Dist: transformers (>=4.25.0)
Requires-Dist: tqdm
Requires-Dist: accelerate (>=0.21.0)
Requires-Dist: safetensors
Provides-Extra: dev
Requires-Dist: black (~=22.0) ; extra == 'dev'
Requires-Dist: ruff (>=0.0.241) ; extra == 'dev'
Requires-Dist: urllib3 (<=2.0.0) ; extra == 'dev'
Requires-Dist: hf-doc-builder ; extra == 'dev'
Provides-Extra: docs_specific
Requires-Dist: hf-doc-builder ; extra == 'docs_specific'
Provides-Extra: quality
Requires-Dist: black (~=22.0) ; extra == 'quality'
Requires-Dist: ruff (>=0.0.241) ; extra == 'quality'
Requires-Dist: urllib3 (<=2.0.0) ; extra == 'quality'
